jxORM/__init__.py
jxORM/orm/__init__.py
jxORM/orm/common.py
jxORM/orm/jxUtils.py
jxORM/orm/orm.py
jxORM/orm/query.py
jxorm-0.3.1.dist-info/LICENSE
jxorm-0.3.1.dist-info/METADATA
jxorm-0.3.1.dist-info/WHEEL
jxorm-0.3.1.dist-info/top_level.txt
jxorm-0.3.1.dist-info/RECORD
