Metadata-Version: 2.1
Name: jxORM
Version: 0.3.1
Summary: jxORM是配套jxWebUI使用的数据库操作库
Home-page: https://blog.csdn.net/jxandrew/article/details/14946353
Author: 徐晓轶
Author-email: andrew@pythonpi.top
Requires-Python: >=3.10
License-File: LICENSE
Requires-Dist: DBUtils
Requires-Dist: pytz
Requires-Dist: PyMySQL
